{
   "pools":[
      {
         "rolls":{
            "min":5,
            "max":6
         },
         "entries":[
            {
               "type":"item",
               "name":"true:grenade",
               "weight":100,
               "functions":[
                  {
                     "function":"set_count",
                     "count":{
                        "min":4,
                        "max":5
                     }
                  }
               ]
            },
            {
               "type":"item",
               "name":"true:proximity_mine_spawn_egg",
               "weight":60,
               "functions":[
                  {
                     "function":"set_count",
                     "count":{
                        "min":2,
                        "max":3
                     }
                  }
               ]
            },          
            {
               "type":"item",
               "name":"true:sentry_gun_bullet_case",
               "weight":100,
               "functions":[
                  {
                     "function":"set_count",
                     "count":{
                        "min":2,
                        "max":4
                     }
                  }
               ]
            },
            {
               "type":"item",
               "name":"true:sentry_gun_base",
               "weight":100,
               "functions":[
                  {
                     "function":"set_count",
                     "count":{
                        "min":1,
                        "max":2
                     }
                  }
               ]
            },
            {
               "type":"item",
               "name":"true:sentry_gun_sensor",
               "weight":100,
               "functions":[
                  {
                     "function":"set_count",
                     "count":{
                        "min":1,
                        "max":2
                     }
                  }
               ]
            },
            {
               "type":"item",
               "name":"true:sentry_gun_barrel",
               "weight":100,
               "functions":[
                  {
                     "function":"set_count",
                     "count":{
                        "min":1,
                        "max":2
                     }
                  }
               ]
            },
            {
               "type":"item",
               "name":"true:battery",
               "weight":100,
               "functions":[
                  {
                     "function":"set_count",
                     "count":{
                        "min":1,
                        "max":3
                     }
                  }
               ]
            },
            {
               "type":"item",
               "name":"true:night_vision_goggles",
               "weight":100,
               "functions":[
                  {
                     "function":"set_count",
                     "count":{
                        "min":1,
                        "max":2
                     }
                  }
               ]
            },
            {
               "type":"item",
               "name":"true:scuba_goggles",
               "weight":100,
               "functions":[
                  {
                     "function":"set_count",
                     "count":{
                        "min":1,
                        "max":2
                     }
                  }
               ]
            },
            {
               "type":"item",
               "name":"true:gas_mask",
               "weight":100,
               "functions":[
                  {
                     "function":"set_count",
                     "count":{
                        "min":1,
                        "max":2
                     }
                  }
               ]
            }
         ]
      },
      {
         "rolls":{
            "min":1,
            "max":2
         },
         "entries":[
            {
               "type":"item",
               "name":"true:combat_body_armor",
               "weight":100,
               "functions":[
                  {
                     "function":"set_count",
                     "count":{
                        "min":1,
                        "max":1
                     }
                  }
               ]
            },
            {
               "type":"item",
               "name":"true:enhanced_combat_body_armor",
               "weight":20,
               "functions":[
                  {
                     "function":"set_count",
                     "count":{
                        "min":1,
                        "max":1
                     }
                  }
               ]
            }
         ]
      },
      {
         "rolls":{
            "min":5,
            "max":6
         },
         "entries":[
            {
               "type":"item",
               "name":"true:ammo_556mm",
               "weight":50,
               "functions":[
                  {
                     "function":"set_count",
                     "count":{
                        "min":12,
                        "max":24
                     }
                  }
               ]
            },
            {
               "type":"item",
               "name":"true:ammo_762mm",
               "weight":30,
               "functions":[
                  {
                     "function":"set_count",
                     "count":{
                        "min":12,
                        "max":24
                     }
                  }
               ]
            },
            {
               "type":"item",
               "name":"true:ammo_300",
               "weight":10,
               "functions":[
                  {
                     "function":"set_count",
                     "count":{
                        "min":12,
                        "max":24
                     }
                  }
               ]
            }
         ]
      },
      {
         "rolls":{
            "min":2,
            "max":3
         },
         "entries":[
            {
               "type":"item",
               "name":"true:ak47",
               "weight":100,
               "functions":[
                  {
                     "function":"set_count",
                     "count":{
                        "min":1,
                        "max":2
                     }
                  }
               ]
            },
            {
               "type":"item",
               "name":"true:hk416",
               "weight":100,
               "functions":[
                  {
                     "function":"set_count",
                     "count":{
                        "min":1,
                        "max":2
                     }
                  }
               ]
            },
            {
               "type":"item",
               "name":"true:scar_l",
               "weight":100,
               "functions":[
                  {
                     "function":"set_count",
                     "count":{
                        "min":1,
                        "max":2
                     }
                  }
               ]
            },
            {
               "type":"item",
               "name":"true:scar_h",
               "weight":100,
               "functions":[
                  {
                     "function":"set_count",
                     "count":{
                        "min":1,
                        "max":2
                     }
                  }
               ]
            },
            {
               "type":"item",
               "name":"true:awm",
               "weight":50,
               "functions":[
                  {
                     "function":"set_count",
                     "count":{
                        "min":1,
                        "max":2
                     }
                  }
               ]
            }
         ]
      }
   ]
}